globalutil/__init__.py
globalutil/filesystem/__init__.py
globalutil/filesystem/inspections/__init__.py
globalutil/filesystem/inspections/analyzer.py
globalutil/filesystem/inspections/extension_finder.py
globalutil/filesystem/inspections/inspect.py
globalutil/filesystem/inspections/integrity.py
globalutil/filesystem/inspections/recent.py
globalutil/filesystem/inspections/search.py
globalutil/filesystem/operations/__init__.py
globalutil/filesystem/operations/archive.py
globalutil/filesystem/operations/backup.py
globalutil/filesystem/operations/code_documenation.py
globalutil/filesystem/operations/file_reader.py
globalutil/filesystem/operations/manager.py
globalutil/filesystem/operations/organizer.py
globalutil/filesystem/operations/rename.py
globalutil/filesystem/operations/sort.py
globalutil-0.4.1.dist-info/LICENSE
globalutil-0.4.1.dist-info/METADATA
globalutil-0.4.1.dist-info/WHEEL
globalutil-0.4.1.dist-info/top_level.txt
globalutil-0.4.1.dist-info/RECORD
