Metadata-Version: 2.1
Name: globalutil
Version: 0.4.1
Summary: A global utility package for all the data sorting and inspection needs.
Home-page: https://github.com/UYousafzai/globalutil
Author: Umar Khan
Author-email: Umar Khan <umaryousafzai9@gmail.com>
License: MIT License
Project-URL: Homepage, https://github.com/UYousafzai/globalutil
Project-URL: Bug Tracker, https://github.com/UYousafzai/globalutil/issues
Keywords: utility,filesystem,sorting,inspection,global
Classifier: License :: OSI Approved :: MIT License
Classifier: Programming Language :: Python
Classifier: Programming Language :: Python :: 3
Classifier: Programming Language :: Python :: 3.6
Classifier: Programming Language :: Python :: 3.7
Classifier: Programming Language :: Python :: 3.8
Classifier: Programming Language :: Python :: 3.9
Classifier: Programming Language :: Python :: 3.10
Classifier: Programming Language :: Python :: 3.11
Classifier: Operating System :: OS Independent
Requires-Python: >=3.6
License-File: LICENSE
